oobabot/__init__.py
oobabot/__main__.py
oobabot/audio_commands.py
oobabot/audio_responder.py
oobabot/bot_commands.py
oobabot/decide_to_respond.py
oobabot/discord_bot.py
oobabot/discord_utils.py
oobabot/discrivener.py
oobabot/discrivener_message.py
oobabot/fancy_logger.py
oobabot/http_client.py
oobabot/image_generator.py
oobabot/ooba_client.py
oobabot/oobabot.py
oobabot/overengineered_settings_parser.py
oobabot/persona.py
oobabot/prompt_generator.py
oobabot/repetition_tracker.py
oobabot/response_stats.py
oobabot/runtime.py
oobabot/sd_client.py
oobabot/settings.py
oobabot/templates.py
oobabot/transcript.py
oobabot/types.py
oobabot/voice_client.py
oobabot-0.2.3.dist-info/LICENSE
oobabot-0.2.3.dist-info/METADATA
oobabot-0.2.3.dist-info/WHEEL
oobabot-0.2.3.dist-info/entry_points.txt
oobabot-0.2.3.dist-info/RECORD
