Metadata-Version: 2.1
Name: oobabot
Version: 0.2.3
Summary: A Discord bot which talks to Large Language Model AIs running on oobabooga's text-generation-webui
Home-page: https://github.com/chrisrude/oobabot
License: MIT
Author: Christopher Rude
Author-email: chris@rudesoftware.net
Requires-Python: >=3.8.1,<4.0.0
Classifier: License :: OSI Approved :: MIT License
Classifier: Programming Language :: Python :: 3
Classifier: Programming Language :: Python :: 3.9
Classifier: Programming Language :: Python :: 3.10
Classifier: Programming Language :: Python :: 3.11
Requires-Dist: aiohttp (>=3.8.4,<4.0.0)
Requires-Dist: discord.py (>=2.2.2,<3.0.0)
Requires-Dist: pysbd (>=0.3.4,<0.4.0)
Requires-Dist: ruamel-yaml (>=0.17.26,<0.18.0)
Project-URL: Repository, https://github.com/chrisrude/oobabot
